LICENSE
MANIFEST.in
README.md
setup.py
django_logs_middleware.egg-info/PKG-INFO
django_logs_middleware.egg-info/SOURCES.txt
django_logs_middleware.egg-info/dependency_links.txt
django_logs_middleware.egg-info/requires.txt
django_logs_middleware.egg-info/top_level.txt
logs/__init__.py
logs/admin.py
logs/app.py
logs/apps.py
logs/engine.py
logs/middleware.py
logs/models.py
logs/tests.py
logs/views.py