Metadata-Version: 1.1
Name: django-logs-middleware
Version: 0.1.2
Summary: Logs registry for services
Home-page: UNKNOWN
Author: Angel Alfaro
Author-email: a3herrera@gmail.com
License: MIT License
Platform: UNKNOWN
Classifier: Development Status :: 4 - Beta
Classifier: Intended Audience :: Developers
Classifier: Topic :: Software Development :: Build Tools
Classifier: License :: OSI Approved :: MIT License
Classifier: Programming Language :: Python :: 3.4
Classifier: Programming Language :: Python :: 3.5
Classifier: Programming Language :: Python :: 3.6
